_richdem.cpython-311-x86_64-linux-gnu.so
richdem/__init__.py
richdem/cli.py
richdem_fork-3.0.0.dist-info/METADATA
richdem_fork-3.0.0.dist-info/top_level.txt
richdem_fork-3.0.0.dist-info/entry_points.txt
richdem_fork-3.0.0.dist-info/WHEEL
richdem_fork-3.0.0.dist-info/RECORD
richdem_fork-3.0.0.dist-info/licenses/LICENSE.txt
