Metadata-Version: 2.4
Name: richdem-fork
Version: 3.0.0
Summary: High-Performance Terrain Analysis
Home-page: https://github.com/quixoticmonk/richdem
Author: Richard Barnes
Author-email: rbarnes@umn.edu
Maintainer: Manu Chandrasekhar
Maintainer-email: manuchandrasekhar@gmail.com
License: GPLv3
Keywords: GIS terrain hydrology geomorphology raster
Classifier: Development Status :: 4 - Beta
Classifier: Environment :: Console
Classifier: Intended Audience :: Developers
Classifier: Intended Audience :: End Users/Desktop
Classifier: Intended Audience :: Education
Classifier: Intended Audience :: Science/Research
Classifier: Intended Audience :: Other Audience
Classifier: License :: OSI Approved :: GNU General Public License v3 (GPLv3)
Classifier: Natural Language :: English
Classifier: Topic :: Scientific/Engineering :: GIS
Classifier: Topic :: Scientific/Engineering :: Information Analysis
Classifier: Topic :: Scientific/Engineering :: Visualization
Classifier: Topic :: Software Development :: Libraries
Classifier: Programming Language :: Python :: 3.10
Classifier: Programming Language :: Python :: 3.11
Classifier: Programming Language :: Python :: 3.12
Requires-Python: >=3.10
License-File: LICENSE.txt
Requires-Dist: numpy<3,>=1.21; python_version >= "3.10"
Requires-Dist: importlib_metadata; python_version < "3.8"
Dynamic: author
Dynamic: author-email
Dynamic: classifier
Dynamic: description
Dynamic: home-page
Dynamic: keywords
Dynamic: license
Dynamic: license-file
Dynamic: maintainer
Dynamic: maintainer-email
Dynamic: requires-dist
Dynamic: requires-python
Dynamic: summary
